bitcoinrpc/__init__.py
bitcoinrpc/authproxy.py
pie_python_bitcoinrpc-2.0.dist-info/LICENSE
pie_python_bitcoinrpc-2.0.dist-info/METADATA
pie_python_bitcoinrpc-2.0.dist-info/WHEEL
pie_python_bitcoinrpc-2.0.dist-info/top_level.txt
pie_python_bitcoinrpc-2.0.dist-info/RECORD
