Metadata-Version: 2.1
Name: pie-python-bitcoinrpc
Version: 2.0
Summary: Enhanced version of python-jsonrpc for use with Bitcoin
Home-page: https://www.github.com/qishuo/pie-python-bitcoinrpc
Author: qishuo
Author-email: <me@qishuo.net>
Maintainer: qishuo
Maintainer-email: <me@qishuo.net>
License: UNKNOWN
Platform: UNKNOWN
Classifier: License :: OSI Approved :: GNU Library or Lesser General Public License (LGPL)
Classifier: Operating System :: OS Independent
License-File: LICENSE
